cubature/__init__.py
cubature/_cubature.cp310-win_amd64.pyd
cubature/_test_integrands.cp310-win_amd64.pyd
cubature/cubature.py
cubature-0.18.8.dist-info/METADATA
cubature-0.18.8.dist-info/WHEEL
cubature-0.18.8.dist-info/top_level.txt
cubature-0.18.8.dist-info/RECORD
